LICENSE.txt
README.md
setup.py
backplane/__init__.py
backplane2_pyclient.egg-info/PKG-INFO
backplane2_pyclient.egg-info/SOURCES.txt
backplane2_pyclient.egg-info/dependency_links.txt
backplane2_pyclient.egg-info/requires.txt
backplane2_pyclient.egg-info/top_level.txt
backplane2_pyclient.egg-info/zip-safe
tests/__init__.py
tests/test_backplane.py