Metadata-Version: 1.0
Name: backplane2-pyclient
Version: 0.2
Summary: Backplane 2 library for python
Home-page: http://github.com/janrain/backplane2-pyclient
Author: George Katsitadze
Author-email: george@janrain.com
License: Apache License 2.0
Keywords: backplane library
Platform: UNKNOWN
